actions/__init__.py
actions/file.py
utils/__init__.py
utils/env_file.py
utils/exit_codes.py
utils/password.py
utils/version.py
cryptenv-0.2.dist-info/LICENSE
cryptenv-0.2.dist-info/METADATA
cryptenv-0.2.dist-info/WHEEL
cryptenv-0.2.dist-info/entry_points.txt
cryptenv-0.2.dist-info/top_level.txt
cryptenv-0.2.dist-info/RECORD
