Metadata-Version: 2.1
Name: cryptenv
Version: 0.2
Summary: A CLI tool to encrypt and decrypt variables in .env files.
Author-email: Vasilis Papadopoulos <vpapadopoulos155@gmail.com>
License: MIT
Project-URL: GitHub, https://github.com/vaspapadopoulos/cryptenv
Keywords: env,encrypt,decrypt
Classifier: Intended Audience :: Developers
Classifier: Intended Audience :: System Administrators
Classifier: Natural Language :: English
Classifier: License :: OSI Approved :: MIT License
Classifier: Programming Language :: Python
Classifier: Programming Language :: Python :: 3
Classifier: Programming Language :: Python :: 3.9
Requires-Python: >=3.9
License-File: LICENSE
Requires-Dist: cryptography (==40.0.2)
